teddecor/__init__.py
teddecor/pprint.py
teddecor/TED/__init__.py
teddecor/TED/color/__init__.py
teddecor/TED/color/colors.py
teddecor/TED/color/xterm_colors.py
teddecor/TED/markup/__init__.py
teddecor/TED/markup/formatting.py
teddecor/TED/markup/markup.py
teddecor/TED/markup/tokens.py
teddecor/decorators/__init__.py
teddecor/decorators/specify.py
teddecor/decorators/utility.py
teddecor/decorators/config/__init__.py
teddecor/decorators/config/config.py
teddecor/decorators/config/config_base.py
teddecor/decorators/config/test.json
teddecor/decorators/config/test.py
teddecor/decorators/config/test.yaml
teddecor/decorators/config/types_default.py
teddecor/logger/LL.py
teddecor/logger/__init__.py
teddecor/logger/encoding.py
teddecor/logger/log.py
teddecor-1.3.1.dist-info/METADATA
teddecor-1.3.1.dist-info/WHEEL
teddecor-1.3.1.dist-info/licenses/LICENSE
teddecor-1.3.1.dist-info/RECORD
