Metadata-Version: 2.1
Name: teddecor
Version: 1.3.1
Summary: Simple python testing framework
Project-URL: Homepage, https://github.com/Tired-Fox/TEDDecor
Project-URL: Documentation, https://tired-fox.github.io/TEDDecor/
Author-email: Tired Fox <zboehm104@gmail.com>
License-File: LICENSE
Classifier: License :: OSI Approved :: MIT License
Classifier: Operating System :: OS Independent
Classifier: Programming Language :: Python :: 3
Requires-Python: >=3.7
